{
	"configurations" : 
	[
		{
			"directories" : 
			[
				{
					"build" : ".",
					"hasInstallRule" : true,
					"jsonFile" : "directory-.-debug-719e958b6f2fca52fac2.json",
					"minimumCMakeVersion" : 
					{
						"string" : "3.10.2"
					},
					"projectIndex" : 0,
					"source" : ".",
					"targetIndexes" : 
					[
						0,
						1,
						2,
						3,
						4,
						5
					]
				}
			],
			"name" : "debug",
			"projects" : 
			[
				{
					"directoryIndexes" : 
					[
						0
					],
					"name" : "tug_turtlebot4",
					"targetIndexes" : 
					[
						0,
						1,
						2,
						3,
						4,
						5
					]
				}
			],
			"targets" : 
			[
				{
					"directoryIndex" : 0,
					"id" : "simple_turtle::@6890427a1f51a3e7e1df",
					"jsonFile" : "target-simple_turtle-debug-193e5b25d2d56491b080.json",
					"name" : "simple_turtle",
					"projectIndex" : 0
				},
				{
					"directoryIndex" : 0,
					"id" : "slam::@6890427a1f51a3e7e1df",
					"jsonFile" : "target-slam-debug-190325b5f5069f5aa595.json",
					"name" : "slam",
					"projectIndex" : 0
				},
				{
					"directoryIndex" : 0,
					"id" : "static_transform_publisher::@6890427a1f51a3e7e1df",
					"jsonFile" : "target-static_transform_publisher-debug-c0d0114fb6af00f1dbfc.json",
					"name" : "static_transform_publisher",
					"projectIndex" : 0
				},
				{
					"directoryIndex" : 0,
					"id" : "tug_turtlebot4_uninstall::@6890427a1f51a3e7e1df",
					"jsonFile" : "target-tug_turtlebot4_uninstall-debug-ddd2d0a193d2ae95f881.json",
					"name" : "tug_turtlebot4_uninstall",
					"projectIndex" : 0
				},
				{
					"directoryIndex" : 0,
					"id" : "tug_wheel_encoder-system::@6890427a1f51a3e7e1df",
					"jsonFile" : "target-tug_wheel_encoder-system-debug-83ff4c47cc334d448f56.json",
					"name" : "tug_wheel_encoder-system",
					"projectIndex" : 0
				},
				{
					"directoryIndex" : 0,
					"id" : "uninstall::@6890427a1f51a3e7e1df",
					"jsonFile" : "target-uninstall-debug-884a5f7fb15f5b81d010.json",
					"name" : "uninstall",
					"projectIndex" : 0
				}
			]
		}
	],
	"kind" : "codemodel",
	"paths" : 
	{
		"build" : "/home/bobo/ros2_ws/build/tug_turtlebot4",
		"source" : "/home/bobo/ros2_ws/src/mr2_public/tug_turtlebot4"
	},
	"version" : 
	{
		"major" : 2,
		"minor" : 3
	}
}
